{"options":{"validator":{"$jsonSchema":{"bsonType":"object","required":["patient","visit","medical","admin","billing","src"],"properties":{"patient":{"bsonType":"object","required":["name","age","gender","blood_type"],"properties":{"name":{"bsonType":"string"},"age":{"bsonType":"int"},"gender":{"enum":["Male","Female"]},"blood_type":{"enum":["A+","A-","B+","B-","AB+","AB-","O+","O-"]}}},"visit":{"bsonType":"object","required":["admission_date","admission_type","room_number"],"properties":{"admission_date":{"bsonType":"date"},"discharge_date":{"bsonType":["date","null"]},"admission_type":{"bsonType":"string"},"room_number":{"bsonType":"int"}}},"medical":{"bsonType":"object","required":["condition","medication","test_results"],"properties":{"condition":{"bsonType":"string"},"medication":{"bsonType":"string"},"test_results":{"bsonType":"string"}}},"admin":{"bsonType":"object","required":["doctor","hospital","insurance_provider"],"properties":{"doctor":{"bsonType":"string"},"hospital":{"bsonType":"string"},"insurance_provider":{"bsonType":"string"}}},"billing":{"bsonType":"object","required":["amount"],"properties":{"amount":{"bsonType":"decimal"}}},"src":{"bsonType":"object","required":["file","ingested_at"],"properties":{"file":{"bsonType":"string"},"ingested_at":{"bsonType":"date"}}}}}},"validationLevel":"moderate","validationAction":"error"},"indexes":[{"v":{"$numberInt":"2"},"key":{"_id":{"$numberInt":"1"}},"name":"_id_"},{"v":{"$numberInt":"2"},"key":{"admin.hospital":{"$numberInt":"1"},"visit.admission_date":{"$numberInt":"1"}},"name":"ix_hospital_admissionDate"},{"v":{"$numberInt":"2"},"key":{"medical.condition":{"$numberInt":"1"}},"name":"ix_condition"},{"v":{"$numberInt":"2"},"key":{"billing.amount":{"$numberInt":"1"}},"name":"ix_amount"},{"v":{"$numberInt":"2"},"key":{"admin.insurance_provider":{"$numberInt":"1"}},"name":"ix_insurer"}],"uuid":"63862d395f1d40ed808857746a016984","collectionName":"encounters","type":"collection"}